refurbished/__init__.py
refurbished/cli.py
refurbished/feedback.py
refurbished/model.py
refurbished/parser.py
refurbished-0.12.0.data/scripts/rfrb
refurbished-0.12.0.dist-info/LICENSE
refurbished-0.12.0.dist-info/METADATA
refurbished-0.12.0.dist-info/WHEEL
refurbished-0.12.0.dist-info/top_level.txt
refurbished-0.12.0.dist-info/RECORD
