Metadata-Version: 2.1
Name: refurbished
Version: 0.12.0
Summary: Library to search refurbished products on the Apple Store
Home-page: https://github.com/zmoog/refurbished
Author: Maurizio Branca
Author-email: maurizio.branca@gmail.com
Classifier: Development Status :: 4 - Beta
Classifier: Intended Audience :: Developers
Classifier: Programming Language :: Python :: 3
Classifier: License :: OSI Approved :: Apache Software License
Classifier: Operating System :: OS Independent
License-File: LICENSE
Requires-Dist: beautifulsoup4>=4.11.1
Requires-Dist: click==8.1.3
Requires-Dist: price-parser==0.3.4
Requires-Dist: pydantic==1.10.4
Requires-Dist: requests>=2.28.1
Requires-Dist: rich>=12.6.0
Provides-Extra: test
Requires-Dist: pytest==7.2.1; extra == "test"
Requires-Dist: black==22.12.0; extra == "test"
Requires-Dist: isort==5.12.0; extra == "test"
Requires-Dist: flake8==6.0.0; extra == "test"
